COPYING
CloseableQueue.py
MANIFEST.in
README.txt
setup.py
CloseableQueue.egg-info/PKG-INFO
CloseableQueue.egg-info/SOURCES.txt
CloseableQueue.egg-info/dependency_links.txt
CloseableQueue.egg-info/top_level.txt
test/__init__.py
test/test_queue.py
test/test_support.py