Metadata-Version: 1.0
Name: CloseableQueue
Version: 0.9.1
Summary:  These classes and functions provide the facility to close a queue and to use it as an iterator.
Home-page: http://github.com/intuited/CloseableQueue
Author: Ted Tibbetts
Author-email: intuited@gmail.com
License: UNKNOWN
Keywords: queue,multithreading,threading,iterator,iterable,iteration
Platform: UNKNOWN
Classifier: Development Status :: 4 - Beta
Classifier: Intended Audience :: Developers
Classifier: License :: OSI Approved :: BSD License
Classifier: Operating System :: OS Independent
Classifier: Programming Language :: Python
Classifier: Programming Language :: Python :: 2
Classifier: Topic :: Software Development :: Libraries :: Python Modules
Classifier: Topic :: Utilities
